iid42/__init__.py
iid42-2025.1.10.1052.dist-info/METADATA
iid42-2025.1.10.1052.dist-info/WHEEL
iid42-2025.1.10.1052.dist-info/licenses/LICENSE
iid42-2025.1.10.1052.dist-info/RECORD
