Metadata-Version: 2.4
Name: iid42
Version: 2025.1.10.1052
Summary: Help building app using Index Integer Date format IID
Project-URL: Homepage, https://github.com/EloiStree/pypi_iid
Project-URL: Issues, https://github.com/EloiStree/pypi_iid
Author-email: Eloi Stree <eloistree@gmail.com>
License-File: LICENSE
Keywords: IID,date,development,index,integer
Classifier: Development Status :: 1 - Planning
Classifier: Operating System :: OS Independent
Classifier: Programming Language :: Python :: 3
Requires-Python: >=3.0
Requires-Dist: asyncio
Requires-Dist: ntplib
Requires-Dist: websockets
